Workbook
Name Slicer_category: #N/A
Name Slicer_Date_Hierarchy: #N/A
Name Slicer_Month: #N/A
Name Slicer_region: #N/A

Sheet Customers
A1: customer_id | B1: customer_name | C1: region | D1: state | E1: city
A2: C1 | B2: Ishaan Verma | C2: South | D2: Kerala | E2: Trivandrum
A3: C2 | B3: Navya Saxena | C3: East | D3: Assam | E3: Dibrugarh
A4: C3 | B4: Meera Gupta | C4: North | D4: Haryana | E4: Faridabad
A5: C4 | B5: Sai Mehta | C5: South | D5: Telangana | E5: Karimnagar
A6: C5 | B6: Ishaan Saxena | C6: South | D6: Kerala | E6: Kochi
A7: C6 | B7: Riya Agarwal | C7: East | D7: Odisha | E7: Rourkela
A8: C7 | B8: Kiara Nair | C8: North | D8: Uttar Pradesh | E8: Noida
A9: C8 | B9: Saanvi Khan | C9: North | D9: Punjab | E9: Ludhiana
A10: C9 | B10: Krishna Reddy | C10: South | D10: Kerala | E10: Kozhikode
A11: C10 | B11: Aarav Verma | C11: West | D11: Gujarat | E11: Ahmedabad
A12: C11 | B12: Atharv Khan | C12: South | D12: Telangana | E12: Hyderabad
... A4001: C4000 | B4001: Aadhya Chopra | C4001: West | D4001: Gujarat | E4001: Ahmedabad

Sheet Products
A1: product_id | B1: product | C1: category | D1: sub_category | E1: unit_price | F1: cost_price
A2: P-1 | B2: Headphones | C2: Electronics | D2: Wireless | E2: 2354.1159 | F2: 1810.7846
A3: P-2 | B3: Laptop | C3: Electronics | D3: Ultrabook | E3: 28502.898 | F3: 20477.836
A4: P-3 | B4: Camera | C4: Electronics | D4: DSLR | E4: 23345.986 | F4: 15772.904
A5: P-4 | B5: AC | C5: Appliances | D5: Window | E5: 23898.369 | F5: 16491.822
A6: P-5 | B6: AC | C6: Appliances | D6: Split | E6: 23457.607 | F6: 17038.832
A7: P-6 | B7: Cooler | C7: Appliances | D7: Personal | E7: 6005.1162 | F7: 4036.1472
A8: P-7 | B8: Phone | C8: Electronics | D8: Android | E8: 12877.548 | F8: 9551.9001
A9: P-8 | B9: Headphones | C9: Electronics | D9: Wireless | E9: 2370.6749 | F9: 1742.1191
A10: P-9 | B10: Tablet | C10: Electronics | D10: Android Tablet | E10: 16482.73 | F10: 12480.812
A11: P-10 | B11: Fan | C11: Appliances | D11: Ceiling | E11: 2136.8181 | F11: 1689.4874
A12: P-11 | B12: Phone | C12: Electronics | D12: Android | E12: 12594.364 | F12: 9909.7268
A13: P-12 | B13: Laptop | C13: Electronics | D13: Ultrabook | E13: 30304.143 | F13: 23998.195
... A201: P-200 | B201: Phone | C201: Electronics | D201: iOS | E201: 11719.595 | F201: 7926.6333

Sheet Orders
A1: order_id | B1: order_date | C1: order_period | D1: customer_id | E1: product_id | F1: category | G1: quantity | H1: discount_pct | I1: unit_price | J1: cost_price
A2: 1 | B2: 45583 | C2: =DATE(YEAR(orders[[#This Row],[order_date]]), MONTH(orders[[#This Row],[order_date]]), 1) -> 45566 | D2: C3841 | E2: P-38 | F2: =VLOOKUP(orders[[#This Row],[product_id]],Products!A:C,3,0) -> Appliances | G2: 3 | H2: 0.064241929 | I2: =VLOOKUP($E2, Products!$A$1:$F$201,MATCH(Orders!I$1,Products!$A$1:$F$1,0),0) -> 2300.9894 | J2: =VLOOKUP($E2, Products!$A$1:$F$201,MATCH(Orders!J$1,Products!$A$1:$F$1,0),0) -> 1726.391
A3: 2 | B3: 45861 | C3: =DATE(YEAR(orders[[#This Row],[order_date]]), MONTH(orders[[#This Row],[order_date]]), 1) -> 45839 | D3: C3691 | E3: P-74 | F3: =VLOOKUP(orders[[#This Row],[product_id]],Products!A:C,3,0) -> Appliances | G3: 2 | H3: 0.13128618 | I3: =VLOOKUP($E3, Products!$A$1:$F$201,MATCH(Orders!I$1,Products!$A$1:$F$1,0),0) -> 5919.3205 | J3: =VLOOKUP($E3, Products!$A$1:$F$201,MATCH(Orders!J$1,Products!$A$1:$F$1,0),0) -> 3972.3071
A4: 3 | B4: 45237 | C4: =DATE(YEAR(orders[[#This Row],[order_date]]), MONTH(orders[[#This Row],[order_date]]), 1) -> 45231 | D4: C3356 | E4: P-73 | F4: =VLOOKUP(orders[[#This Row],[product_id]],Products!A:C,3,0) -> Electronics | G4: 1 | H4: 0.14195344 | I4: =VLOOKUP($E4, Products!$A$1:$F$201,MATCH(Orders!I$1,Products!$A$1:$F$1,0),0) -> 2632.5533 | J4: =VLOOKUP($E4, Products!$A$1:$F$201,MATCH(Orders!J$1,Products!$A$1:$F$1,0),0) -> 1732.3161
A5: 4 | B5: 45483 | C5: =DATE(YEAR(orders[[#This Row],[order_date]]), MONTH(orders[[#This Row],[order_date]]), 1) -> 45474 | D5: C2610 | E5: P-17 | F5: =VLOOKUP(orders[[#This Row],[product_id]],Products!A:C,3,0) -> Appliances | G5: 1 | H5: 0.053792034 | I5: =VLOOKUP($E5, Products!$A$1:$F$201,MATCH(Orders!I$1,Products!$A$1:$F$1,0),0) -> 24966.708 | J5: =VLOOKUP($E5, Products!$A$1:$F$201,MATCH(Orders!J$1,Products!$A$1:$F$1,0),0) -> 19868.706
A6: 5 | B6: 45898 | C6: =DATE(YEAR(orders[[#This Row],[order_date]]), MONTH(orders[[#This Row],[order_date]]), 1) -> 45870 | D6: C2083 | E6: P-106 | F6: =VLOOKUP(orders[[#This Row],[product_id]],Products!A:C,3,0) -> Electronics | G6: 2 | H6: 0.16987799 | I6: =VLOOKUP($E6, Products!$A$1:$F$201,MATCH(Orders!I$1,Products!$A$1:$F$1,0),0) -> 12041.083 | J6: =VLOOKUP($E6, Products!$A$1:$F$201,MATCH(Orders!J$1,Products!$A$1:$F$1,0),0) -> 7946.6428
A7: 6 | B7: 45183 | C7: =DATE(YEAR(orders[[#This Row],[order_date]]), MONTH(orders[[#This Row],[order_date]]), 1) -> 45170 | D7: C224 | E7: P-48 | F7: =VLOOKUP(orders[[#This Row],[product_id]],Products!A:C,3,0) -> Electronics | G7: 2 | H7: 0.24297361 | I7: =VLOOKUP($E7, Products!$A$1:$F$201,MATCH(Orders!I$1,Products!$A$1:$F$1,0),0) -> 19089.562 | J7: =VLOOKUP($E7, Products!$A$1:$F$201,MATCH(Orders!J$1,Products!$A$1:$F$1,0),0) -> 12552.84
A8: 7 | B8: 45459 | C8: =DATE(YEAR(orders[[#This Row],[order_date]]), MONTH(orders[[#This Row],[order_date]]), 1) -> 45444 | D8: C2716 | E8: P-177 | F8: =VLOOKUP(orders[[#This Row],[product_id]],Products!A:C,3,0) -> Electronics | G8: 3 | H8: 0.14869884 | I8: =VLOOKUP($E8, Products!$A$1:$F$201,MATCH(Orders!I$1,Products!$A$1:$F$1,0),0) -> 32533.34 | J8: =VLOOKUP($E8, Products!$A$1:$F$201,MATCH(Orders!J$1,Products!$A$1:$F$1,0),0) -> 22734.712
A9: 8 | B9: 44978 | C9: =DATE(YEAR(orders[[#This Row],[order_date]]), MONTH(orders[[#This Row],[order_date]]), 1) -> 44958 | D9: C2441 | E9: P-171 | F9: =VLOOKUP(orders[[#This Row],[product_id]],Products!A:C,3,0) -> Electronics | G9: 1 | H9: 0.14219834 | I9: =VLOOKUP($E9, Products!$A$1:$F$201,MATCH(Orders!I$1,Products!$A$1:$F$1,0),0) -> 30008.649 | J9: =VLOOKUP($E9, Products!$A$1:$F$201,MATCH(Orders!J$1,Products!$A$1:$F$1,0),0) -> 19907.237
A10: 9 | B10: 46017 | C10: =DATE(YEAR(orders[[#This Row],[order_date]]), MONTH(orders[[#This Row],[order_date]]), 1) -> 45992 | D10: C2456 | E10: P-84 | F10: =VLOOKUP(orders[[#This Row],[product_id]],Products!A:C,3,0) -> Appliances | G10: 1 | H10: 0.075403855 | I10: =VLOOKUP($E10, Products!$A$1:$F$201,MATCH(Orders!I$1,Products!$A$1:$F$1,0),0) -> 6227.1352 | J10: =VLOOKUP($E10, Products!$A$1:$F$201,MATCH(Orders!J$1,Products!$A$1:$F$1,0),0) -> 4146.7708
A11: 10 | B11: 45226 | C11: =DATE(YEAR(orders[[#This Row],[order_date]]), MONTH(orders[[#This Row],[order_date]]), 1) -> 45200 | D11: C3775 | E11: P-7 | F11: =VLOOKUP(orders[[#This Row],[product_id]],Products!A:C,3,0) -> Electronics | G11: 3 | H11: 0.15879524 | I11: =VLOOKUP($E11, Products!$A$1:$F$201,MATCH(Orders!I$1,Products!$A$1:$F$1,0),0) -> 12877.548 | J11: =VLOOKUP($E11, Products!$A$1:$F$201,MATCH(Orders!J$1,Products!$A$1:$F$1,0),0) -> 9551.9001
A12: 11 | B12: 45598 | C12: =DATE(YEAR(orders[[#This Row],[order_date]]), MONTH(orders[[#This Row],[order_date]]), 1) -> 45597 | D12: C1412 | E12: P-196 | F12: =VLOOKUP(orders[[#This Row],[product_id]],Products!A:C,3,0) -> Electronics | G12: 2 | H12: 0.12730625 | I12: =VLOOKUP($E12, Products!$A$1:$F$201,MATCH(Orders!I$1,Products!$A$1:$F$1,0),0) -> 19562.355 | J12: =VLOOKUP($E12, Products!$A$1:$F$201,MATCH(Orders!J$1,Products!$A$1:$F$1,0),0) -> 13782.495
A13: 12 | B13: 45704 | C13: =DATE(YEAR(orders[[#This Row],[order_date]]), MONTH(orders[[#This Row],[order_date]]), 1) -> 45689 | D13: C1720 | E13: P-126 | F13: =VLOOKUP(orders[[#This Row],[product_id]],Products!A:C,3,0) -> Appliances | G13: 2 | H13: 0.065515981 | I13: =VLOOKUP($E13, Products!$A$1:$F$201,MATCH(Orders!I$1,Products!$A$1:$F$1,0),0) -> 5983.7309 | J13: =VLOOKUP($E13, Products!$A$1:$F$201,MATCH(Orders!J$1,Products!$A$1:$F$1,0),0) -> 4205.6433
... A15001: 15000 | B15001: 45069 | C15001: =DATE(YEAR(orders[[#This Row],[order_date]]), MONTH(orders[[#This Row],[order_date]]), 1) -> 45047 | D15001: C3 | E15001: P-20 | F15001: =VLOOKUP(orders[[#This Row],[product_id]],Products!A:C,3,0) -> Electronics | G15001: 1 | H15001: 0.12154444 | I15001: =VLOOKUP($E15001, Products!$A$1:$F$201,MATCH(Orders!I$1,Products!$A$1:$F$1,0),0) -> 2441.7406 | J15001: =VLOOKUP($E15001, Products!$A$1:$F$201,MATCH(Orders!J$1,Products!$A$1:$F$1,0),0) -> 1934.1374

Sheet Targets
A1: year | B1: month | C1: target_period | D1: target_sales
A2: 2023 | B2: Jan | C2: =DATEVALUE("1-"&targets[[#This Row],[month]]&"-"&targets[[#This Row],[year]]) -> 44927 | D2: 9273593.5
A3: 2023 | B3: Feb | C3: =DATEVALUE("1-"&targets[[#This Row],[month]]&"-"&targets[[#This Row],[year]]) -> 44958 | D3: 9042772.2
A4: 2023 | B4: Mar | C4: =DATEVALUE("1-"&targets[[#This Row],[month]]&"-"&targets[[#This Row],[year]]) -> 44986 | D4: 8836142.1
A5: 2023 | B5: Apr | C5: =DATEVALUE("1-"&targets[[#This Row],[month]]&"-"&targets[[#This Row],[year]]) -> 45017 | D5: 13711380
A6: 2023 | B6: May | C6: =DATEVALUE("1-"&targets[[#This Row],[month]]&"-"&targets[[#This Row],[year]]) -> 45047 | D6: 13413276
A7: 2023 | B7: Jun | C7: =DATEVALUE("1-"&targets[[#This Row],[month]]&"-"&targets[[#This Row],[year]]) -> 45078 | D7: 10977345
A8: 2023 | B8: Jul | C8: =DATEVALUE("1-"&targets[[#This Row],[month]]&"-"&targets[[#This Row],[year]]) -> 45108 | D8: 8121056.8
A9: 2023 | B9: Aug | C9: =DATEVALUE("1-"&targets[[#This Row],[month]]&"-"&targets[[#This Row],[year]]) -> 45139 | D9: 9008276.6
A10: 2023 | B10: Sep | C10: =DATEVALUE("1-"&targets[[#This Row],[month]]&"-"&targets[[#This Row],[year]]) -> 45170 | D10: 8490341.7
A11: 2023 | B11: Oct | C11: =DATEVALUE("1-"&targets[[#This Row],[month]]&"-"&targets[[#This Row],[year]]) -> 45200 | D11: 11928707
A12: 2023 | B12: Nov | C12: =DATEVALUE("1-"&targets[[#This Row],[month]]&"-"&targets[[#This Row],[year]]) -> 45231 | D12: 10385984
A13: 2023 | B13: Dec | C13: =DATEVALUE("1-"&targets[[#This Row],[month]]&"-"&targets[[#This Row],[year]]) -> 45261 | D13: 8077477.5
... A37: 2025 | B37: Dec | C37: =DATEVALUE("1-"&targets[[#This Row],[month]]&"-"&targets[[#This Row],[year]]) -> 45992 | D37: 9889949.2

Sheet Calculations
A16: KPIs | B16: Net Sales | C16: Target Achievement % | D16: Profit Margin % | E16: Average Order Value | F16: Total Orders
B17: 1.174875e+08 | C17: 0.90233522 | D17: 0.14639912 | E17: 22964.718 | F17: 5116
B18: =GETPIVOTDATA("[Measures].[Net Sales]",$B$16) -> 1.174875e+08 | C18: =GETPIVOTDATA("[Measures].[Target Achievement %]",$B$16) -> 0.90233522 | D18: =GETPIVOTDATA("[Measures].[Profit Margin %]",$B$16) -> 0.14639912 | E18: =GETPIVOTDATA("[Measures].[Average Order Value]",$B$16) -> 22964.718 | F18: =GETPIVOTDATA("[Measures].[Total Orders]",$B$16) -> 5116
B22: Net Sales LY | C22: Target Achievement % LY | D22: Profit Margin % LY | E22: Average Order Value LY | F22: Total Orders LY
B23: 1.1632124e+08 | C23: 0.95101547 | D23: 0.14620698 | E23: 23268.902 | F23: 4999
B24: =GETPIVOTDATA("[Measures].[Net Sales LY]",$B$22) -> 1.1632124e+08 | C24: =GETPIVOTDATA("[Measures].[Target Achievement % LY]",$B$22) -> 0.95101547 | D24: =GETPIVOTDATA("[Measures].[Profit Margin % LY]",$B$22) -> 0.14620698 | E24: =GETPIVOTDATA("[Measures].[Average Order Value LY]",$B$22) -> 23268.902 | F24: =GETPIVOTDATA("[Measures].[Total Orders LY]",$B$22) -> 4999
B27: Net Sales delta | C27: Target Achievement delta | D27: Profit Margin delta | E27: Average Order Value delta | F27: Total Orders delta
B28: 0.010026176 | C28: -0.048680253 | D28: 0.00019213767 | E28: -0.013072547 | F28: 0.023404681
B29: =GETPIVOTDATA("[Measures].[Net Sales delta]",$B$27) -> 0.010026176 | C29: =GETPIVOTDATA("[Measures].[Target Achievement delta]",$B$27) -> -0.048680253 | D29: =GETPIVOTDATA("[Measures].[Profit Margin delta]",$B$27) -> 0.00019213767 | E29: =GETPIVOTDATA("[Measures].[Average Order Value delta]",$B$27) -> -0.013072547 | F29: =GETPIVOTDATA("[Measures].[Total Orders delta]",$B$27) -> 0.023404681
A36: Target vs Actuals | B36: Row Labels | C36: Total Target | D36: Net Sales
B37: January | C37: 9779838.2 | D37: 8676947.4
B38: February | C38: 8373718.2 | D38: 7025267
B39: March | C39: 8944477.9 | D39: 8691832.5
B40: April | C40: 14405590 | D40: 12453738
B41: May | C41: 13747851 | D41: 12476513
B42: June | C42: 12426358 | D42: 12501127
B43: July | C43: 8302370.7 | D43: 7612268.6
B44: August | C44: 9104021.7 | D44: 8786183.2
B45: September | C45: 10232821 | D45: 8684859.7
B46: October | C46: 11691807 | D46: 9835748
B47: November | C47: 13305025 | D47: 11634080
B48: December | C48: 9889949.2 | D48: 9108934.7
B49: Grand Total | C49: 1.3020383e+08 | D49: 1.174875e+08
A55: Regional Sales & Profitability | B55: Row Labels | C55: Net Sales | D55: Weighted Discount % | E55: Profit Margin %
B56: East | C56: 29222146 | D56: 0.15326617 | E56: 0.14917828
B57: North | C57: 29334043 | D57: 0.15476435 | E57: 0.14879649
B58: South | C58: 29241574 | D58: 0.15612349 | E58: 0.1466308
B59: West | C59: 29689736 | D59: 0.15687688 | E59: 0.14106689
B60: Grand Total | C60: 1.174875e+08 | D60: 0.15526608 | E60: 0.14639912
A73: Category wise Total Revenue and Orders | B73: Row Labels | C73: Net Sales
B74: Appliances | C74: 34376398
B75: Electronics | C75: 83111101
B76: Grand Total | C76: 1.174875e+08
B78: Row Labels | C78: Total Orders
B79: Appliances | C79: 1822
B80: Electronics | C80: 3294
B81: Grand Total | C81: 5116
A89: Top States by Order Count | B89: Row Labels | C89: Total Orders
B90: Bihar | C90: 332
B91: Haryana | C91: 341
B92: Maharashtra | C92: 419
B93: Gujarat | C93: 435
B94: Rajasthan | C94: 435
B95: Grand Total | C95: 1962
A106: Profit Margin vs Weighted Discount % | B106: Row Labels | C106: Weighted Discount % | D106: Profit Margin | F106: Products | G106: Weighted Discount % | H106: Profit Margin
B107: AC | C107: 0.09910258 | D107: 5219884 | F107: =B107 -> AC | G107: =GETPIVOTDATA("[Measures].[Weighted Discount %]",$B$106,"[products].[product]","[products].[product].&["&B107&"]") -> 0.09910258 | H107: =GETPIVOTDATA("[Measures].[Profit Margin]",$B$106,"[products].[product]","[products].[product].&["&B107&"]") -> 5219884
B108: Camera | C108: 0.17496097 | D108: 1996003.8 | F108: =B108 -> Camera | G108: =GETPIVOTDATA("[Measures].[Weighted Discount %]",$B$106,"[products].[product]","[products].[product].&["&B108&"]") -> 0.17496097 | H108: =GETPIVOTDATA("[Measures].[Profit Margin]",$B$106,"[products].[product]","[products].[product].&["&B108&"]") -> 1996003.8
B109: Cooler | C109: 0.10167973 | D109: 1061643.7 | F109: =B109 -> Cooler | G109: =GETPIVOTDATA("[Measures].[Weighted Discount %]",$B$106,"[products].[product]","[products].[product].&["&B109&"]") -> 0.10167973 | H109: =GETPIVOTDATA("[Measures].[Profit Margin]",$B$106,"[products].[product]","[products].[product].&["&B109&"]") -> 1061643.7
B110: Fan | C110: 0.10057825 | D110: 372925.21 | F110: =B110 -> Fan | G110: =GETPIVOTDATA("[Measures].[Weighted Discount %]",$B$106,"[products].[product]","[products].[product].&["&B110&"]") -> 0.10057825 | H110: =GETPIVOTDATA("[Measures].[Profit Margin]",$B$106,"[products].[product]","[products].[product].&["&B110&"]") -> 372925.21
B111: Headphones | C111: 0.1785308 | D111: 219892.99 | F111: =B111 -> Headphones | G111: =GETPIVOTDATA("[Measures].[Weighted Discount %]",$B$106,"[products].[product]","[products].[product].&["&B111&"]") -> 0.1785308 | H111: =GETPIVOTDATA("[Measures].[Profit Margin]",$B$106,"[products].[product]","[products].[product].&["&B111&"]") -> 219892.99
B112: Laptop | C112: 0.17770888 | D112: 5082878.4 | F112: =B112 -> Laptop | G112: =GETPIVOTDATA("[Measures].[Weighted Discount %]",$B$106,"[products].[product]","[products].[product].&["&B112&"]") -> 0.17770888 | H112: =GETPIVOTDATA("[Measures].[Profit Margin]",$B$106,"[products].[product]","[products].[product].&["&B112&"]") -> 5082878.4
B113: Phone | C113: 0.1749147 | D113: 1536474.5 | F113: =B113 -> Phone | G113: =GETPIVOTDATA("[Measures].[Weighted Discount %]",$B$106,"[products].[product]","[products].[product].&["&B113&"]") -> 0.1749147 | H113: =GETPIVOTDATA("[Measures].[Profit Margin]",$B$106,"[products].[product]","[products].[product].&["&B113&"]") -> 1536474.5
B114: Tablet | C114: 0.17457872 | D114: 1710363.8 | F114: =B114 -> Tablet | G114: =GETPIVOTDATA("[Measures].[Weighted Discount %]",$B$106,"[products].[product]","[products].[product].&["&B114&"]") -> 0.17457872 | H114: =GETPIVOTDATA("[Measures].[Profit Margin]",$B$106,"[products].[product]","[products].[product].&["&B114&"]") -> 1710363.8
B115: Grand Total | C115: 0.15526608 | D115: 17200066
A124: Revenue to Profit Bridge | B124: Gross Sales | C124: Total Discount | D124: Net Sales | E124: Total Cost | F124: Profit Margin
B125: 1.3908226e+08 | C125: 21594757 | D125: 1.174875e+08 | E125: 1.0028743e+08 | F125: 17200066
B126: =GETPIVOTDATA("[Measures].[Gross Sales]",$B$124) -> 1.3908226e+08 | C126: =-GETPIVOTDATA("[Measures].[Total Discount]",$B$124) -> -21594757 | D126: =GETPIVOTDATA("[Measures].[Net Sales]",$B$124) -> 1.174875e+08 | E126: =-GETPIVOTDATA("[Measures].[Total Cost]",$B$124) -> -1.0028743e+08 | F126: =GETPIVOTDATA("[Measures].[Profit Margin]",$B$124) -> 17200066
A142: Target Achievement Trend % | B142: Month | C142: Target Achievement % | E142: Month | F142: Actual | G142: Red | H142: Yellow | I142: Green
B143: December | C143: 0.92102947 | E143: =B143 -> December | F143: =C143 -> 0.92102947 | G143: =IF(F143<0.85,F143, NA()) -> #N/A | H143: =IF(AND(F143>=0.85,F143<0.95), F143, NA()) -> 0.92102947 | I143: =IF(F143>=0.95, F143, NA()) -> #N/A
B144: November | C144: 0.87441251 | E144: =B144 -> November | F144: =C144 -> 0.87441251 | G144: =IF(F144<0.85,F144, NA()) -> #N/A | H144: =IF(AND(F144>=0.85,F144<0.95), F144, NA()) -> 0.87441251 | I144: =IF(F144>=0.95, F144, NA()) -> #N/A
B145: October | C145: 0.84125131 | E145: =B145 -> October | F145: =C145 -> 0.84125131 | G145: =IF(F145<0.85,F145, NA()) -> 0.84125131 | H145: =IF(AND(F145>=0.85,F145<0.95), F145, NA()) -> #N/A | I145: =IF(F145>=0.95, F145, NA()) -> #N/A
B146: September | C146: 0.84872587 | E146: =B146 -> September | F146: =C146 -> 0.84872587 | G146: =IF(F146<0.85,F146, NA()) -> 0.84872587 | H146: =IF(AND(F146>=0.85,F146<0.95), F146, NA()) -> #N/A | I146: =IF(F146>=0.95, F146, NA()) -> #N/A
B147: August | C147: 0.96508812 | E147: =B147 -> August | F147: =C147 -> 0.96508812 | G147: =IF(F147<0.85,F147, NA()) -> #N/A | H147: =IF(AND(F147>=0.85,F147<0.95), F147, NA()) -> #N/A | I147: =IF(F147>=0.95, F147, NA()) -> 0.96508812
B148: July | C148: 0.91687892 | E148: =B148 -> July | F148: =C148 -> 0.91687892 | G148: =IF(F148<0.85,F148, NA()) -> #N/A | H148: =IF(AND(F148>=0.85,F148<0.95), F148, NA()) -> 0.91687892 | I148: =IF(F148>=0.95, F148, NA()) -> #N/A
B149: June | C149: 1.006017 | E149: =B149 -> June | F149: =C149 -> 1.006017 | G149: =IF(F149<0.85,F149, NA()) -> #N/A | H149: =IF(AND(F149>=0.85,F149<0.95), F149, NA()) -> #N/A | I149: =IF(F149>=0.95, F149, NA()) -> 1.006017
B150: May | C150: 0.90752458 | E150: =B150 -> May | F150: =C150 -> 0.90752458 | G150: =IF(F150<0.85,F150, NA()) -> #N/A | H150: =IF(AND(F150>=0.85,F150<0.95), F150, NA()) -> 0.90752458 | I150: =IF(F150>=0.95, F150, NA()) -> #N/A
B151: April | C151: 0.86450734 | E151: =B151 -> April | F151: =C151 -> 0.86450734 | G151: =IF(F151<0.85,F151, NA()) -> #N/A | H151: =IF(AND(F151>=0.85,F151<0.95), F151, NA()) -> 0.86450734 | I151: =IF(F151>=0.95, F151, NA()) -> #N/A
B152: March | C152: 0.97175403 | E152: =B152 -> March | F152: =C152 -> 0.97175403 | G152: =IF(F152<0.85,F152, NA()) -> #N/A | H152: =IF(AND(F152>=0.85,F152<0.95), F152, NA()) -> #N/A | I152: =IF(F152>=0.95, F152, NA()) -> 0.97175403
B153: February | C153: 0.83896625 | E153: =B153 -> February | F153: =C153 -> 0.83896625 | G153: =IF(F153<0.85,F153, NA()) -> 0.83896625 | H153: =IF(AND(F153>=0.85,F153<0.95), F153, NA()) -> #N/A | I153: =IF(F153>=0.95, F153, NA()) -> #N/A
B154: January | C154: 0.88722811 | E154: =B154 -> January | F154: =C154 -> 0.88722811 | G154: =IF(F154<0.85,F154, NA()) -> #N/A | H154: =IF(AND(F154>=0.85,F154<0.95), F154, NA()) -> 0.88722811 | I154: =IF(F154>=0.95, F154, NA()) -> #N/A
B155: Grand Total | C155: 0.90233522

Sheet Dashboard
G8: ss
AF14: `
